pythonbible_parser/__init__.py
pythonbible_parser/bible_parser.py
pythonbible_parser/errors.py
pythonbible_parser/json_converter.py
pythonbible_parser/data/asv/books.json
pythonbible_parser/data/asv/verses.json
pythonbible_parser/data/kjv/books.json
pythonbible_parser/data/kjv/verses.json
pythonbible_parser/osis/__init__.py
pythonbible_parser/osis/constants.py
pythonbible_parser/osis/old_osis_parser.py
pythonbible_parser/osis/osis_book_parser.py
pythonbible_parser/osis/osis_parser.py
pythonbible_parser/osis/osis_utilities.py
pythonbible_parser/osis/sandbox.py
pythonbible_parser/osis/versions/asv.xml
pythonbible_parser/osis/versions/kjv.xml
pythonbible_parser-0.0.6.dist-info/LICENSE
pythonbible_parser-0.0.6.dist-info/WHEEL
pythonbible_parser-0.0.6.dist-info/METADATA
pythonbible_parser-0.0.6.dist-info/RECORD
