Metadata-Version: 2.1
Name: pythonbible_parser
Version: 0.0.6
Summary: The pythonbible-parser library.
Home-page: https://github.com/avendesora/pythonbible-parser
Author: Nathan Patton
Author-email: npatton@gmail.com
Requires-Python: >=3.7
Classifier: Intended Audience :: Information Technology
Classifier: Intended Audience :: Developers
Classifier: Operating System :: OS Independent
Classifier: Topic :: Software Development :: Libraries :: Python Modules
Classifier: Topic :: Software Development :: Libraries
Classifier: Topic :: Software Development
Classifier: Programming Language :: Python
Classifier: Programming Language :: Python :: 3
Classifier: Programming Language :: Python :: 3 :: Only
Classifier: Programming Language :: Python :: 3.7
Classifier: Programming Language :: Python :: 3.8
Classifier: Programming Language :: Python :: 3.9
Classifier: License :: OSI Approved :: MIT License
Requires-Dist: defusedxml >=0.7.1
Requires-Dist: pythonbible ==0.9.1
Requires-Dist: pre-commit >=2.20.0 ; extra == "dev"
Requires-Dist: pytest >=7.1.2 ; extra == "test"
Requires-Dist: pytest-cov >=3.0.0 ; extra == "test"
Project-URL: Documentation, https://github.com/avendesora/pythonbible-parser
Project-URL: Source, https://github.com/avendesora/pythonbible-parser
Provides-Extra: all
Provides-Extra: dev
Provides-Extra: doc
Provides-Extra: test
